fcaBayesian/__init__.py
fcabayesian-0.3.0.dist-info/entry_points.txt
fcabayesian-0.3.0.dist-info/METADATA
fcabayesian-0.3.0.dist-info/WHEEL
fcabayesian-0.3.0.dist-info/RECORD
