Metadata-Version: 2.1
Name: fcabayesian
Version: 0.3.0
Summary: 
Author: JuanDiegoAvila
Author-email: avi20090@uvg.edu.gt
Requires-Python: >=3.10,<4.0
Classifier: Programming Language :: Python :: 3
Classifier: Programming Language :: Python :: 3.10
Classifier: Programming Language :: Python :: 3.11
Requires-Dist: pgmpy (>=0.1.15,<0.2.0)
